[{"id":"rec0znmQnWwTCwO7K","fields":{"Name":"Eden Shochat","Company":["recF71OHfTcuMMUNM"],"Role":"Partner","Start Date":"2013-01-01","Is Current":true,"Person":["recu548lRI1JvcL70"]}},{"id":"rec1aDRozlS3m0mA9","fields":{"Name":"Gal Sagie","Company":["recrq6Q9pfzOcydq2"],"Role":"Co-Founder","Start Date":"2022-01-01","Is Founder":true,"Is Current":true,"Notable Achievement":"$40M raised","Notes":"Protects $100B+ assets","Person":["reck0oYAs6miViu8L"]}},{"id":"rec36bsnfiy4bAhJz","fields":{"Name":"Mooly Sagiv","Company":["recPIVFl2SqcY582B"],"Role":"Founder","Start Date":"2018-01-01","Is Founder":true,"Is Current":true,"Notable Achievement":"Secures $25B+ DeFi","Person":["recdfLaRrJ0v9EWEm"]}},{"id":"rec3VJ4g3Hi5uA1Sa","fields":{"Name":"Dov Moran","Company":["recjlnIqqHgeO7E4g"],"Role":"Founder & CEO","Start Date":"1989-01-01","End Date":"2006-07-01","Is Founder":true,"Notable Achievement":"$1.6B exit to SanDisk","Notes":"Invented USB Flash Drive","Person":["reczSq0X3wVUIQG6P"]}},{"id":"rec4bNOiMnupjxQxo","fields":{"Name":"Nir Zuk","Company":["recJp6behB2K5lToj"],"Role":"Founder & CTO","Start Date":"2005-01-01","Is Founder":true,"Is Current":true,"Notable Achievement":"Built $100B+ company","Person":["recD6gm5fZ9s90M6Q"]}},{"id":"rec5E4qk2HLUZtApn","fields":{"Name":"Oren Zeev","Company":["rec50JuKhPFT84owl"],"Role":"Founder","Start Date":"2008-01-01","Is Founder":true,"Is Current":true,"Notes":"Houzz investor","Person":["recIQAZAFxaGAqRet"]}},{"id":"rec7ZAZiq8l6X3H2u","fields":{"Name":"Omer Goldberg","Company":["recfb2cVyClkaI6SD"],"Role":"Founder & CEO","Start Date":"2021-01-01","Is Founder":true,"Is Current":true,"Notable Achievement":"$79M raised","Notes":"DeFi risk management","Person":["rec1DRa2A7cEBtt0a"]}},{"id":"rec7egRWMFdVD1Lzm","fields":{"Name":"Matan Sitbon","Company":["recHOA74lzqh9R8c9"],"Role":"Founder & CEO","Start Date":"2022-01-01","Is Founder":true,"Is Current":true,"Notes":"Built on EigenLayer","Person":["recjnx1exaBdHL5VN"]}},{"id":"rec7zr0xDQ9pJGWE6","fields":{"Name":"Dan Caspi","Company":["recrq6Q9pfzOcydq2"],"Role":"Co-Founder","Start Date":"2022-01-01","Is Founder":true,"Is Current":true,"Notes":"Hypernative - $100B+ protected","Person":["recj1e1A4rL2c8Iej"]}},{"id":"rec8IlfNexY5u94EU","fields":{"Name":"Guy Zyskind","Company":["recgsJJL6q5ZXQXhH"],"Role":"Co-Founder","Start Date":"2023-01-01","Is Founder":true,"Is Current":true,"Notes":"Previously Secret Network/Enigma","Person":["reczky37MCfMkt0T7"]}},{"id":"rec8SwPUAoMIvqrz4","fields":{"Name":"Guy Itzhaki","Company":["recgsJJL6q5ZXQXhH"],"Role":"Founder","Start Date":"2023-01-01","Is Founder":true,"Is Current":true,"Notes":"FHEenix - Collider portfolio","Person":["rec7di4u0Bg7hLqZQ"]}},{"id":"recAHWCxWplhQShn4","fields":{"Name":"Nir Zuk","Company":["rec1umsiFg35vSD8o"],"Role":"Engineer","Start Date":"1994-01-01","End Date":"1999-01-01","Notable Achievement":"Stateful inspection patent","Person":["recD6gm5fZ9s90M6Q"]}},{"id":"recBtt1IgYhUecRkx","fields":{"Name":"Shlomo Kramer","Company":["rec1umsiFg35vSD8o"],"Role":"Co-Founder & VP Engineering","Start Date":"1993-01-01","End Date":"1998-01-01","Is Founder":true,"Notable Achievement":"Invented firewall","Person":["rectgMDB7V9G6WlJz"]}},{"id":"recCwXtli1GffZQGX","fields":{"Name":"Michael Shaulov","Company":["rec1umsiFg35vSD8o"],"Role":"VP Mobile Security","Start Date":"2010-01-01","End Date":"2017-01-01","Notable Achievement":"Lacoon acquisition","Person":["rec5D87LVWEh7ZTt6"]}},{"id":"recDTbEg0sHGBbcHp","fields":{"Name":"Eyal Hertzog","Company":["recMHGuPTQGkVtN9W"],"Role":"Co-Founder","Start Date":"2017-01-01","Is Founder":true,"Is Current":true,"Notable Achievement":"Invented AMM","Notes":"$153M raised","Person":["recVACaTKAC8cghfi"]}},{"id":"recDn4TuaC88WFS22","fields":{"Name":"Roy Reznik","Role":"Engineering Lead","Start Date":"2015-07-01","End Date":"2020-01-01","Person":["recPcf2d1jpFl3yeA"]}},{"id":"recE2bMPu3t1ACnyl","fields":{"Name":"Hillel Fuld","Role":"Tech Influencer","Start Date":"2010-01-01","Is Current":true,"Notes":"Very responsive on Twitter","Person":["reccn5yCJZOMtmUy2"]}},{"id":"recEK2Kx0r4xBTfly","fields":{"Name":"Yehuda Lindell","Company":["recaWIo9xh08qnewz"],"Role":"Co-Founder","Start Date":"2014-01-01","End Date":"2022-01-01","Is Founder":true,"Notable Achievement":"$100M exit to Coinbase","Person":["recikBwkHLkASRFgS"]}},{"id":"recFYeiuLs8BQvfGH","fields":{"Name":"Udi Wertheimer","Company":["recfGWtveya63T0PM"],"Role":"Founder","Start Date":"2023-01-01","Is Founder":true,"Is Current":true,"Notes":"Bitcoin Ordinals pioneer","Person":["recPXWuFlnuIeyyz3"]}},{"id":"recK2zcFyxGR9fv57","fields":{"Name":"Ami Luttwak","Company":["recr3zyBhynRsDCM5"],"Role":"Co-Founder & CTO","Start Date":"2012-01-01","End Date":"2015-07-01","Is Founder":true,"Person":["rec6FSLkRtbd57IHN"]}},{"id":"recKSWJcCeAbj24Ur","fields":{"Name":"Dov Moran","Company":["recdzfR8KP3PRvb2i"],"Role":"Managing Partner","Start Date":"2015-01-01","Is Founder":true,"Is Current":true,"Notes":"Deep tech VC","Person":["reczSq0X3wVUIQG6P"]}},{"id":"recMfpC02JNIruAYw","fields":{"Name":"Assaf Rappaport","Role":"Officer","Start Date":"2004-01-01","End Date":"2009-01-01","Notable Achievement":"8200 alumni","Person":["reclIEjfBf1LE75gd"]}},{"id":"recMuYTu7DHOl5azz","fields":{"Name":"Uri Levine","Company":["rec8geNbSIlC6i6AF"],"Role":"Co-Founder","Start Date":"2006-01-01","End Date":"2013-06-11","Is Founder":true,"Notable Achievement":"$1.3B exit to Google","Person":["recaHu3WjTArAl8DR"]}},{"id":"recNQChvT6mHrhXtV","fields":{"Name":"Roy Reznik","Company":["rec16Q9Kryxz6heVn"],"Role":"Co-Founder & VP R&D","Start Date":"2020-01-01","Is Founder":true,"Is Current":true,"Person":["recPcf2d1jpFl3yeA"]}},{"id":"recOYviriIP2HrdSu","fields":{"Name":"Yehuda Lindell","Role":"Professor","Start Date":"1999-01-01","Is Current":true,"Notable Achievement":"MPC pioneer","Person":["recikBwkHLkASRFgS"]}},{"id":"recOebshjI34Kogmg","fields":{"Name":"Avishay Ovadia","Company":["recLLlneaPv57Le5i"],"Role":"Founding Partner","Start Date":"2018-01-01","Is Founder":true,"Is Current":true,"Notes":"Israeli crypto super-connector","Person":["rectJfFBoLzyL0k8f"]}},{"id":"recPifS3gmEpXC52n","fields":{"Name":"Yarden Shechter","Company":["rec70tan65XEXdJfY"],"Role":"Founder","Start Date":"2023-01-01","Is Founder":true,"Is Current":true,"Notes":"AVS infrastructure","Person":["recPj5VuhpDCdQW6u"]}},{"id":"recPqbKYM63ZMcWSS","fields":{"Name":"Shlomo Kramer","Company":["recuDdgycF6bygv4N"],"Role":"Founder & CEO","Start Date":"2015-01-01","Is Founder":true,"Is Current":true,"Notable Achievement":"Created SASE category","Notes":"$773M raised","Person":["rectgMDB7V9G6WlJz"]}},{"id":"recPxkVqLC66Z2hHq","fields":{"Name":"Gil Dibner","Company":["recNm2OqWlm6AYKLH"],"Role":"Founder","Start Date":"2017-01-01","Is Founder":true,"Is Current":true,"Notable Achievement":"Solo GP","Notes":"Makes own decisions","Person":["recDUA4xZOsJiXppW"]}},{"id":"recQINcQUaAzNH1BY","fields":{"Name":"Assaf Rappaport","Company":["rec16Q9Kryxz6heVn"],"Role":"Co-Founder & CEO","Start Date":"2020-01-01","Is Founder":true,"Is Current":true,"Notable Achievement":"$32B exit to Google","Notes":"Fastest growing cyber company ever","Person":["reclIEjfBf1LE75gd"]}},{"id":"recRRgOv3fg12V2WJ","fields":{"Name":"Uri Levine","Company":["rec5vsZy4AMfvqL8y"],"Role":"Chairman","Start Date":"2012-01-01","Is Current":true,"Notes":"Fintech","Person":["recaHu3WjTArAl8DR"]}},{"id":"recRo214RsW1OolWR","fields":{"Name":"Nadav Zafrir","Role":"Commander","Start Date":"2005-01-01","End Date":"2009-01-01","Notable Achievement":"8200 Commander","Person":["recystn6ZXKDPQUeB"]}},{"id":"recRrR09pkSxz42T8","fields":{"Name":"Ami Luttwak","Role":"CTO Security","Start Date":"2015-07-01","End Date":"2020-01-01","Person":["rec6FSLkRtbd57IHN"]}},{"id":"recTIH1ZRZO11cbix","fields":{"Name":"Itay Malinger","Company":["recDI2pR0dlWBrKY2"],"Role":"Co-Founder & CEO","Start Date":"2018-01-01","End Date":"2021-03-01","Is Founder":true,"Notable Achievement":"$200M exit to PayPal","Person":["recJEjEwDCHoyNh3w"]}},{"id":"recTISWVOv4q4dMe0","fields":{"Name":"Yaron Velner","Company":["recfMyKcw5UUwSvgG"],"Role":"Founder","Start Date":"2020-01-01","Is Founder":true,"Is Current":true,"Notes":"DeFi OG","Person":["recrddcvAiVEm3VyB"]}},{"id":"recUa4LfCH6pIfrgF","fields":{"Name":"Yinon Costica","Company":["recr3zyBhynRsDCM5"],"Role":"Co-Founder","Start Date":"2012-01-01","End Date":"2015-07-01","Is Founder":true,"Person":["recs5vSWAJuYMEFRt"]}},{"id":"recWy5j7ujRq9jmHI","fields":{"Name":"Dan Yadlin","Company":["recDI2pR0dlWBrKY2"],"Role":"Co-Founder","Start Date":"2018-01-01","End Date":"2021-03-01","Is Founder":true,"Notable Achievement":"$200M PayPal exit","Person":["rec85KuULsDhGNdAM"]}},{"id":"recXQosHs5NLF6oTC","fields":{"Name":"Yoni Assia","Company":["recuGsnVYpIWDQMPx"],"Role":"Founder & CEO","Start Date":"2007-01-01","Is Founder":true,"Is Current":true,"Notes":"eToro founder - 35M users","Person":["recY8HlRPCwDbTkeM"]}},{"id":"recYNb04VdObSa2nA","fields":{"Name":"Nadav Zafrir","Company":["recREi1inShZZCeqX"],"Role":"Founder & CEO","Start Date":"2014-01-01","End Date":"2024-01-01","Is Founder":true,"Notable Achievement":"Cyber foundry","Person":["recystn6ZXKDPQUeB"]}},{"id":"recaC9F7I11AX0aOw","fields":{"Name":"Eli Ben-Sasson","Company":["recg1Do9u8vc6GvBt"],"Role":"Co-Founder & President","Start Date":"2018-01-01","Is Founder":true,"Is Current":true,"Notable Achievement":"$8B valuation","Person":["recJexrGBh6YpXDFu"]}},{"id":"recafAmzX4EfYFJdd","fields":{"Name":"Pavel Berengoltz","Company":["recIwcZmHAf08jdgU"],"Role":"Co-Founder & CTO","Start Date":"2018-01-01","Is Founder":true,"Is Current":true,"Notable Achievement":"$8B valuation","Person":["recx1fcIWR3aLybFb"]}},{"id":"recayjJf9JUI1T27N","fields":{"Name":"Yinon Costica","Company":["rec16Q9Kryxz6heVn"],"Role":"Co-Founder & VP Product","Start Date":"2020-01-01","Is Founder":true,"Is Current":true,"Person":["recs5vSWAJuYMEFRt"]}},{"id":"recbEK05YjcZdDUCL","fields":{"Name":"Josh Schwartz","Company":["recg3boJcAeqqFifD"],"Role":"Founder & CEO","Start Date":"2021-01-01","End Date":"2025-11-01","Is Founder":true,"Notable Achievement":"$100M Paxos acquisition","Person":["reccT27j629myuN3G"]}},{"id":"reccD0NXzndcoaXB4","fields":{"Name":"Ido Ben-Natan","Company":["recIqFr5pEa28IABK"],"Role":"Co-Founder & CEO","Start Date":"2022-01-01","Is Founder":true,"Is Current":true,"Notable Achievement":"$83M raised","Notes":"Web3 security leader","Person":["rec7V7nbQ8T8sfudi"]}},{"id":"recco6zYDoB6CmuyS","fields":{"Name":"Or Dadosh","Company":["recxIShRH64Fk45DV"],"Role":"Founder","Start Date":"2022-01-01","Is Founder":true,"Is Current":true,"Notes":"Venn - Collider portfolio","Person":["rec1XBp7Lrx7al2W6"]}},{"id":"rece0BfyQvDskDuzu","fields":{"Name":"Adam Benayoun","Company":["recLLlneaPv57Le5i"],"Role":"Founding Partner","Start Date":"2018-01-01","Is Founder":true,"Is Current":true,"Person":["recvphZSZ4vi0Neem"]}},{"id":"recez6LZ1Ml6tDv4M","fields":{"Name":"Uri Kolodny","Company":["recg1Do9u8vc6GvBt"],"Role":"Co-Founder & CEO","Start Date":"2018-01-01","Is Founder":true,"Is Current":true,"Person":["reciweoKF98C2vG7J"]}},{"id":"recfRuVz3aY72j3uh","fields":{"Name":"Tal Be'ery","Company":["recMMB0BpQtSuwLo0"],"Role":"Co-Founder & CTO","Start Date":"2018-01-01","Is Founder":true,"Is Current":true,"Notable Achievement":"Zero hacks","Person":["receGRH7BfLoEmvDK"]}},{"id":"rechyJKN1FAYHMGjO","fields":{"Name":"Yinon Costica","Role":"Product Lead","Start Date":"2015-07-01","End Date":"2020-01-01","Person":["recs5vSWAJuYMEFRt"]}},{"id":"recj8pthkj5FJ6IyH","fields":{"Name":"Ouriel Ohayon","Company":["recMMB0BpQtSuwLo0"],"Role":"Co-Founder & CEO","Start Date":"2018-01-01","Is Founder":true,"Is Current":true,"Notable Achievement":"2M+ users","Notes":"MPC wallet","Person":["recfSzjh9EWhDloa8"]}},{"id":"recjfrM7AZtCUgJW5","fields":{"Name":"Ben Samocha","Company":["recybpAQErAbtCRZB"],"Role":"CEO","Start Date":"2020-01-01","Is Founder":true,"Is Current":true,"Notes":"EXISTING CONTACT via Reuven","Person":["recVOuP0z45rngL6r"]}},{"id":"recjseNBKs1QrJ82T","fields":{"Name":"Roy Reznik","Company":["recr3zyBhynRsDCM5"],"Role":"Co-Founder","Start Date":"2012-01-01","End Date":"2015-07-01","Is Founder":true,"Person":["recPcf2d1jpFl3yeA"]}},{"id":"reckHoqWzTlZmhjoX","fields":{"Name":"Michael Shaulov","Company":["recIwcZmHAf08jdgU"],"Role":"Co-Founder & CEO","Start Date":"2018-01-01","Is Founder":true,"Is Current":true,"Notable Achievement":"$8B valuation, zero security incidents","Person":["rec5D87LVWEh7ZTt6"]}},{"id":"recl0txHzToMtUSJm","fields":{"Name":"Assaf Rappaport","Role":"GM Security","Start Date":"2015-07-01","End Date":"2020-01-01","Notable Achievement":"Post-Adallom acquisition","Person":["reclIEjfBf1LE75gd"]}},{"id":"recmy8gLAo9xwTDDs","fields":{"Name":"Yossi Vardi","Role":"Investor","Start Date":"1970-01-01","Is Current":true,"Notable Achievement":"ICQ, 80+ investments","Notes":"Israeli tech godfather","Person":["recOD2RNyzrGL5GfD"]}},{"id":"recn2pGTnvnw8smV2","fields":{"Name":"Yonatan Hayun","Company":["recfb2cVyClkaI6SD"],"Role":"Co-Founder","Start Date":"2021-01-01","Is Founder":true,"Is Current":true,"Person":["recZDJPDqVrGYohbf"]}},{"id":"recnbrXG66YN2WCJw","fields":{"Name":"Nimrod Lehavi","Company":["recWygOnNJPgkGr6V"],"Role":"Founder & CEO","Start Date":"2014-01-01","End Date":"2021-01-01","Is Founder":true,"Notable Achievement":"$200-250M Nuvei exit","Person":["recTg5ZG5DECM3TA4"]}},{"id":"recoDW9Y6yNTmoUnv","fields":{"Name":"Nadav Zafrir","Company":["rec1umsiFg35vSD8o"],"Role":"CEO","Start Date":"2024-12-01","Is Current":true,"Notable Achievement":"Took over from Gil Shwed","Person":["recystn6ZXKDPQUeB"]}},{"id":"recopUpmMm8XlGsc5","fields":{"Name":"Dov Moran","Company":["recCz7WqxN4QhwazK"],"Role":"Founder & CEO","Start Date":"2007-01-01","End Date":"2011-02-01","Is Founder":true,"Notes":"$130M raised, patents to Google","Person":["reczSq0X3wVUIQG6P"]}},{"id":"recpBiEzcGCLdYraq","fields":{"Name":"Lior Lamesh","Company":["recrSsrDDOPqhmpbi"],"Role":"Founder & CEO","Start Date":"2018-01-01","End Date":"2022-01-01","Is Founder":true,"Notable Achievement":"Galaxy acquisition","Person":["recO1lXVcQ4mK0zlm"]}},{"id":"recqUORgAmRBkjg7T","fields":{"Name":"Shauli Rejwan","Company":["rec7FJDX5PHLU5jPL"],"Role":"Partner","Start Date":"2020-01-01","Is Current":true,"Notes":"Web3 Dev Underground sponsor","Person":["rec6QPW2hepdgbZ6I"]}},{"id":"recqYvl6UsOh1ZTsC","fields":{"Name":"Sebastian Lehrer","Company":["recLLlneaPv57Le5i"],"Role":"Investor","Start Date":"2020-01-01","Is Current":true,"Notes":"Report author","Person":["recPOnKXTTf6IP17w"]}},{"id":"recqzJ5TWEYBXMr4k","fields":{"Name":"Ehud Shabtai","Company":["rec8geNbSIlC6i6AF"],"Role":"Co-Founder & CTO","Start Date":"2006-01-01","End Date":"2013-06-11","Is Founder":true,"Notable Achievement":"Technical co-founder","Person":["recTRaBd6MRrIM7PQ"]}},{"id":"recsuquc1E35STewN","fields":{"Name":"Adam Efrima","Company":["recVxyfJW914n0f7q"],"Role":"Founder","Start Date":"2020-01-01","Is Founder":true,"Is Current":true,"Notes":"ETH staking infrastructure","Person":["recf71xyAQxVJnvXL"]}},{"id":"rectP4zqVtH3KMXWI","fields":{"Name":"Raz Niv","Company":["recIqFr5pEa28IABK"],"Role":"Co-Founder","Start Date":"2022-01-01","Is Founder":true,"Is Current":true,"Person":["recXwGVI4eOj52pxm"]}},{"id":"rectoBHY2YRErtRvD","fields":{"Name":"Michael Eisenberg","Company":["recF71OHfTcuMMUNM"],"Role":"Partner","Start Date":"2013-01-01","Is Current":true,"Notes":"Writes about crypto","Person":["recFg3ntJHsjDnWy6"]}},{"id":"recu4i1H93l06GHBU","fields":{"Name":"Dr. Yonatan Sompolinsky","Company":["rec8albS0SCkNtwhP"],"Role":"Founder","Start Date":"2017-01-01","Is Founder":true,"Is Current":true,"Notes":"Kaspa founder - GHOST protocol","Person":["recx2BO5R1rJQzWqv"]}},{"id":"recuB5qPjaMSoj3tO","fields":{"Name":"Ido Ben-Natan","Role":"Officer","Start Date":"2012-01-01","End Date":"2017-01-01","Person":["rec7V7nbQ8T8sfudi"]}},{"id":"recuVAFUvGZErUekA","fields":{"Name":"Eli Ben-Sasson","Role":"Professor","Start Date":"2001-01-01","Is Current":true,"Notable Achievement":"Invented STARKs","Notes":"Cryptography research","Person":["recJexrGBh6YpXDFu"]}},{"id":"recwRz1FAsdsf5lCH","fields":{"Name":"Yishay Harel","Company":["recSbgrYvcTyYgx2A"],"Role":"Founder","Start Date":"2022-01-01","Is Founder":true,"Is Current":true,"Notes":"Modular blockchain","Person":["recO1kmZWi5gxQNn3"]}},{"id":"recwiZPR2Agvn7O0y","fields":{"Name":"Idan Ofrat","Company":["recIwcZmHAf08jdgU"],"Role":"Co-Founder","Start Date":"2018-01-01","Is Founder":true,"Is Current":true,"Person":["recJg0ejjyvYdOW82"]}},{"id":"recyV9Mvnf9WjPmMb","fields":{"Name":"Gigi Levy-Weiss","Company":["rectGyTiDGl5SmPQk"],"Role":"General Partner","Start Date":"2015-01-01","Is Current":true,"Notes":"Prolific angel","Person":["rec0ebT3VWWWRW3wX"]}},{"id":"recyco6EB1W3lKT1X","fields":{"Name":"Gil Shwed","Company":["rec1umsiFg35vSD8o"],"Role":"Executive Chairman","Start Date":"2024-12-01","Is Founder":true,"Is Current":true,"Notes":"Transitioned from CEO","Person":["rec9QHHrftPXqCq4Q"]}},{"id":"recz6zgpDUpBzjuh1","fields":{"Name":"Assaf Rappaport","Company":["recr3zyBhynRsDCM5"],"Role":"Co-Founder & CEO","Start Date":"2012-01-01","End Date":"2015-07-01","Is Founder":true,"Notable Achievement":"$320M exit to Microsoft","Person":["reclIEjfBf1LE75gd"]}},{"id":"recz8imBm0ZZ5iDPd","fields":{"Name":"Dovi Frances","Company":["recjkqqVNLTcWtASM"],"Role":"Founder","Start Date":"2015-01-01","Is Founder":true,"Is Current":true,"Notes":"Backed Fireblocks early","Person":["recW4gaCjYgIFm7Eu"]}},{"id":"recz9Td9ZSwtx8iBX","fields":{"Name":"Ami Luttwak","Company":["rec16Q9Kryxz6heVn"],"Role":"Co-Founder & CTO","Start Date":"2020-01-01","Is Founder":true,"Is Current":true,"Person":["rec6FSLkRtbd57IHN"]}},{"id":"reczAFe28wbwrnfM8","fields":{"Name":"Shlomo Kramer","Company":["recbTGSXywtgVq4cb"],"Role":"Founder & CEO","Start Date":"2002-01-01","End Date":"2014-01-01","Is Founder":true,"Notable Achievement":"$2.1B exit to Thoma Bravo","Person":["rectgMDB7V9G6WlJz"]}},{"id":"reczwIbzWqePjX3Dg","fields":{"Name":"Gil Shwed","Company":["rec1umsiFg35vSD8o"],"Role":"Founder & CEO","Start Date":"1993-01-01","End Date":"2024-12-01","Is Founder":true,"Notable Achievement":"Invented firewall","Notes":"Israel Prize laureate","Person":["rec9QHHrftPXqCq4Q"]}}]